yatts.py
yatts-1.0.0.dist-info/LICENSE
yatts-1.0.0.dist-info/METADATA
yatts-1.0.0.dist-info/WHEEL
yatts-1.0.0.dist-info/top_level.txt
yatts-1.0.0.dist-info/RECORD
