Metadata-Version: 2.1
Name: yatts
Version: 1.0.0
Summary: Styles terminal text
Home-page: https://github.com/xelorabb/yatts
Author: xelorabb
Author-email: xelorabb@gmail.com
License: MIT
Keywords: python,color,text,style,terminal,console
Platform: UNKNOWN
Classifier: Intended Audience :: Developers
Classifier: Programming Language :: Python :: 3.9
Classifier: Operating System :: OS Independent
License-File: LICENSE
